openai_summarize/__init__.py
openai_summarize/openai_summarize.py
openai_summarize-0.1.4.dist-info/METADATA
openai_summarize-0.1.4.dist-info/WHEEL
openai_summarize-0.1.4.dist-info/top_level.txt
openai_summarize-0.1.4.dist-info/RECORD
