Metadata-Version: 2.1
Name: openai-summarize
Version: 0.1.4
Summary: A package for summarizing text using OpenAI
Author: Kix Panganiban
Author-email: Kix Panganiban <kixpanganiban@protonmail.com>
Project-URL: Homepage, https://github.com/kixpanganiban/openai-summarize-py
Project-URL: Bug Tracker, https://github.com/kixpanganiban/openai-summarize-py/issues
Classifier: Programming Language :: Python :: 3
Classifier: License :: OSI Approved :: MIT License
Classifier: Operating System :: OS Independent
Requires-Python: >=3.6
Requires-Dist: aiohttp (==3.8.4)
Requires-Dist: aiosignal (==1.3.1)
Requires-Dist: async-timeout (==4.0.2)
Requires-Dist: attrs (==22.2.0)
Requires-Dist: certifi (==2022.12.7)
Requires-Dist: charset-normalizer (==3.1.0)
Requires-Dist: frozenlist (==1.3.3)
Requires-Dist: idna (==3.4)
Requires-Dist: multidict (==6.0.4)
Requires-Dist: openai (==0.27.2)
Requires-Dist: regex (==2022.10.31)
Requires-Dist: requests (==2.28.2)
Requires-Dist: tiktoken (==0.3.2)
Requires-Dist: tqdm (==4.65.0)
Requires-Dist: urllib3 (==1.26.15)
Requires-Dist: yarl (==1.8.2)
